webgestalt/__init__.py
webgestalt-0.1.0.dist-info/METADATA
webgestalt-0.1.0.dist-info/WHEEL
webgestalt-0.1.0.dist-info/RECORD
