Metadata-Version: 2.1
Name: webgestalt
Version: 0.1.0
Summary: Place holder for WebGestalt package. Please see WebGestaltPy for the current official package.
Requires-Python: >=3.8
